pip_helpers/__init__.py
pip_helpers-0.6.post3.dist-info/DESCRIPTION.rst
pip_helpers-0.6.post3.dist-info/METADATA
pip_helpers-0.6.post3.dist-info/RECORD
pip_helpers-0.6.post3.dist-info/WHEEL
pip_helpers-0.6.post3.dist-info/metadata.json
pip_helpers-0.6.post3.dist-info/pbr.json
pip_helpers-0.6.post3.dist-info/top_level.txt
