Metadata-Version: 2.0
Name: pip-helpers
Version: 0.6.post3
Summary: Helper functions for installing, etc. using `pip`
Home-page: http://github.com/wheeler-microfluidics/pip_helpers.git
Author: Christian Fobel
Author-email: christian@fobel.net
License: GPLv2
Platform: UNKNOWN
Requires-Dist: natsort
Requires-Dist: pip (>=6.0)
Requires-Dist: requests
